gradflow/__init__.py
gradflow/autograd.py
gradflow/data.py
gradflow/init.py
gradflow/nn.py
gradflow/ops.py
gradflow/optim.py
gradflow-0.0.1.dist-info/LICENSE
gradflow-0.0.1.dist-info/METADATA
gradflow-0.0.1.dist-info/WHEEL
gradflow-0.0.1.dist-info/top_level.txt
gradflow-0.0.1.dist-info/RECORD
