Metadata-Version: 2.1
Name: gradflow
Version: 0.0.1
Summary: A simple, scalable and efficient deep learning framework.
Home-page: https://github.com/kcxain/gradflow
Author: kcxain
Author-email: kcxain@gmail.com
License: Apache License 2.0
Keywords: auto-gradient,deep-learning
Platform: UNKNOWN
Classifier: Programming Language :: Python :: 3
Classifier: License :: OSI Approved :: MIT License
Classifier: Operating System :: OS Independent
Requires-Dist: numpy (<1.24.0)
Requires-Dist: setuptools (==45.2.0)
Requires-Dist: typing-extensions (==4.5.0)
